event_voxel_builder-0.0.4.dist-info/METADATA
event_voxel_builder-0.0.4.dist-info/WHEEL
event_voxel_builder-0.0.4.dist-info/licenses/LICENSE
event_voxel_builder/__init__.py
event_voxel_builder/event_voxel_builder.abi3.so
event_voxel_builder-0.0.4.dist-info/RECORD
