Metadata-Version: 2.3
Name: event_voxel_builder
Version: 0.0.4
Classifier: Development Status :: 3 - Alpha
Classifier: Programming Language :: Python
Classifier: Programming Language :: Rust
Classifier: License :: OSI Approved :: GNU Affero General Public License v3 or later (AGPLv3+)
Requires-Dist: numpy
License-File: LICENSE
Summary: Fast event voxel builder
Home-Page: https://codeberg.org/ybh1998/EventVoxelBuilder/
Author: Bohan Yu
Author-email: ybh1998@protonmail.com
License: AGPL-3.0-or-later
Requires-Python: >=3.7
Project-URL: homepage, https://codeberg.org/ybh1998/EventVoxelBuilder/
Project-URL: documentation, https://ybh1998.codeberg.page/EventVoxelBuilder/
